phonetree/__init__.py
phonetree/phonetree.py
phonetree-1.3.1.dist-info/LICENSE
phonetree-1.3.1.dist-info/METADATA
phonetree-1.3.1.dist-info/WHEEL
phonetree-1.3.1.dist-info/top_level.txt
phonetree-1.3.1.dist-info/RECORD
