Metadata-Version: 2.1
Name: phonetree
Version: 1.3.1
Summary: A phone-tree like menu system for text-based interfaces
Author-email: Leandro Lima <leandro@lls-software.com>
Project-URL: Homepage, https://github.com/leandropls/phonetree
Project-URL: Bug Tracker, https://github.com/leandropls/phonetree/issues
Classifier: Development Status :: 4 - Beta
Classifier: Intended Audience :: Developers
Classifier: License :: OSI Approved :: MIT License
Classifier: Programming Language :: Python :: 3 :: Only
Classifier: Topic :: Communications :: Chat
Classifier: Topic :: Software Development :: Libraries :: Application Frameworks
Classifier: Operating System :: OS Independent
Requires-Python: >=3.10
License-File: LICENSE
Requires-Dist: rapidfuzz (>=2.13.7)
